TRSehirler/Sehirler.py
TRSehirler/__init__.py
TRSehirler/Veriler/sehirler.json
TRSehirler/Veriler/ilceler/adana.json
TRSehirler/Veriler/ilceler/adiyaman.json
TRSehirler/Veriler/ilceler/afyon.json
TRSehirler/Veriler/ilceler/agri.json
TRSehirler/Veriler/ilceler/aksaray.json
TRSehirler/Veriler/ilceler/amasya.json
TRSehirler/Veriler/ilceler/ankara.json
TRSehirler/Veriler/ilceler/antalya.json
TRSehirler/Veriler/ilceler/ardahan.json
TRSehirler/Veriler/ilceler/artvin.json
TRSehirler/Veriler/ilceler/aydin.json
TRSehirler/Veriler/ilceler/balikesir.json
TRSehirler/Veriler/ilceler/bartin.json
TRSehirler/Veriler/ilceler/batman.json
TRSehirler/Veriler/ilceler/bayburt.json
TRSehirler/Veriler/ilceler/bilecik.json
TRSehirler/Veriler/ilceler/bingol.json
TRSehirler/Veriler/ilceler/bitlis.json
TRSehirler/Veriler/ilceler/bolu.json
TRSehirler/Veriler/ilceler/burdur.json
TRSehirler/Veriler/ilceler/bursa.json
TRSehirler/Veriler/ilceler/canakkale.json
TRSehirler/Veriler/ilceler/cankiri.json
TRSehirler/Veriler/ilceler/corum.json
TRSehirler/Veriler/ilceler/denizli.json
TRSehirler/Veriler/ilceler/diyarbakir.json
TRSehirler/Veriler/ilceler/duzce.json
TRSehirler/Veriler/ilceler/edirne.json
TRSehirler/Veriler/ilceler/elazig.json
TRSehirler/Veriler/ilceler/erzincan.json
TRSehirler/Veriler/ilceler/erzurum.json
TRSehirler/Veriler/ilceler/eskisehir.json
TRSehirler/Veriler/ilceler/gaziantep.json
TRSehirler/Veriler/ilceler/giresun.json
TRSehirler/Veriler/ilceler/gumushane.json
TRSehirler/Veriler/ilceler/hakkari.json
TRSehirler/Veriler/ilceler/hatay.json
TRSehirler/Veriler/ilceler/igdir.json
TRSehirler/Veriler/ilceler/isparta.json
TRSehirler/Veriler/ilceler/istanbul.json
TRSehirler/Veriler/ilceler/izmir.json
TRSehirler/Veriler/ilceler/kahramanmaras.json
TRSehirler/Veriler/ilceler/karabuk.json
TRSehirler/Veriler/ilceler/karaman.json
TRSehirler/Veriler/ilceler/kars.json
TRSehirler/Veriler/ilceler/kastamonu.json
TRSehirler/Veriler/ilceler/kayseri.json
TRSehirler/Veriler/ilceler/kilis.json
TRSehirler-0.1.8.dist-info/LICENSE
TRSehirler-0.1.8.dist-info/METADATA
TRSehirler-0.1.8.dist-info/WHEEL
TRSehirler-0.1.8.dist-info/top_level.txt
TRSehirler-0.1.8.dist-info/RECORD
