Metadata-Version: 2.1
Name: TRSehirler
Version: 0.1.8
Summary: Türkiye Cumhuriyeti Devleti Şehirlerini; İl, Plaka, Telefon veya İlçe bilgisinden bulun..
Home-page: https://github.com/keyiflerolsun/TRSehirler
Author: keyiflerolsun
Author-email: keyiflerolsun@gmail.com
License: GPLv3+
Keywords: TRSehirler,KekikAkademi,keyiflerolsun
Classifier: Development Status :: 5 - Production/Stable
Classifier: License :: OSI Approved :: GNU General Public License v3 or later (GPLv3+)
Classifier: Programming Language :: Python :: 3
Requires-Python: >=3.10
License-File: LICENSE
Requires-Dist: setuptools
Requires-Dist: wheel
Requires-Dist: Kekik
Requires-Dist: tinydb
Requires-Dist: tabulate
